file_parser/__init__.py
file_parser/audio_parser.py
file_parser/categorizer.py
file_parser/cli.py
file_parser/pdf_parser.py
multimodal_parsers-0.1.6.dist-info/licenses/LICENSE
multimodal_parsers-0.1.6.dist-info/METADATA
multimodal_parsers-0.1.6.dist-info/WHEEL
multimodal_parsers-0.1.6.dist-info/entry_points.txt
multimodal_parsers-0.1.6.dist-info/top_level.txt
multimodal_parsers-0.1.6.dist-info/RECORD
